Metadata-Version: 2.1
Name: YMAPILoader
Version: 0.1.5
Summary: Yandex Metrica API data loader
Home-page: UNKNOWN
Author: Sergey Gorbachev
License: UNKNOWN
Platform: UNKNOWN
Classifier: Programming Language :: Python :: 3.3
Classifier: License :: OSI Approved :: MIT License
Classifier: Operating System :: OS Independent
Requires-Python: >=3.3
License-File: LICENSE
